<?xml version="1.0" encoding="utf-8"?>
<annotation>
	
  
	<folder>VOC</folder>
	
  
	<filename>000776201021547.jpg</filename>
	
  
	<object_num>1</object_num>
	
  
	<size>
		
    
		<width>2000</width>
		
    
		<height>1040</height>
		
    
		<depth>3</depth>
		
  
	</size>
	
  
	<object>
		
    
		<name>NonmetallicFire</name>
		
    
		<difficult>0</difficult>
		
    
		<bndbox>
			
      
			<xmin>181</xmin>
			
      
			<ymin>728</ymin>
			
      
			<xmax>264</xmax>
			
      
			<ymax>839
</ymax>
			
    
		</bndbox>
		
  
	</object>
	

</annotation>
