<?xml version="1.0" encoding="utf-8"?>
<annotation>
	
  
	<folder>VOC</folder>
	
  
	<filename>003059101026076.jpg</filename>
	
  
	<object_num>1</object_num>
	
  
	<size>
		
    
		<width>472</width>
		
    
		<height>1040</height>
		
    
		<depth>3</depth>
		
  
	</size>
	
  
	<object>
		
    
		<name>NonmetallicFire</name>
		
    
		<difficult>0</difficult>
		
    
		<bndbox>
			
      
			<xmin>11</xmin>
			
      
			<ymin>587</ymin>
			
      
			<xmax>83</xmax>
			
      
			<ymax>677
</ymax>
			
    
		</bndbox>
		
  
	</object>
	

</annotation>
